ascii_maze_benchmark/__init__.py
ascii_maze_benchmark/benchmark_runner.py
ascii_maze_benchmark/generate_maze_script.py
ascii_maze_benchmark/maze.py
ascii_maze_benchmark/visualization.py
ascii_maze_benchmark-0.1.0.dist-info/METADATA
ascii_maze_benchmark-0.1.0.dist-info/WHEEL
ascii_maze_benchmark-0.1.0.dist-info/entry_points.txt
ascii_maze_benchmark-0.1.0.dist-info/licenses/LICENSE
ascii_maze_benchmark-0.1.0.dist-info/RECORD
