Metadata-Version: 2.4
Name: ascii-maze-benchmark
Version: 0.1.0
Summary: A benchmark for testing LLM performance at solving ascii mazes.
Author-email: Jeremiah England <englandtuning@gmail.com>
License-File: LICENSE
Requires-Python: >=3.13
Requires-Dist: click>=8.1.7
Requires-Dist: diskcache>=5.6.3
Requires-Dist: matplotlib>=3.10.1
Requires-Dist: numpy>=2.2.4
Requires-Dist: python-dotenv>=1.1.0
Requires-Dist: requests>=2.32.3
